setup.py
ts/__init__.py
ts/inference.py
tss_coco.egg-info/PKG-INFO
tss_coco.egg-info/SOURCES.txt
tss_coco.egg-info/dependency_links.txt
tss_coco.egg-info/top_level.txt