Metadata-Version: 2.1
Name: tss-coco
Version: 1.0
Summary: ts: Test Setup
Home-page:  
Author: Dechin
Author-email: dechin.phy@gmail.com
License: UNKNOWN
Platform: UNKNOWN
Requires-Python: >=3.5.0
